tenint/__init__.py
tenint/cli.py
tenint/connector.py
tenint/models/__init__.py
tenint/models/callback.py
tenint/models/configuration.py
tenint/models/credentials.py
tenint/models/marketplace.py
tenint/models/pyproject.py
tenint/templates/Dockerfile
tenint/templates/connector.py
tenint/templates/pyproject.toml
tenint/templates/test_connector.py
tenint-1.0.3.dist-info/METADATA
tenint-1.0.3.dist-info/WHEEL
tenint-1.0.3.dist-info/entry_points.txt
tenint-1.0.3.dist-info/RECORD
