Metadata-Version: 2.4
Name: tenint
Version: 1.0.3
Summary: Add your description here
Author-email: Tenable Ecosystem Support <ecosystem-support@tenable.com>
Requires-Python: >=3.12
Requires-Dist: email-validator>=2.2.0
Requires-Dist: pydantic-settings>=2.6.1
Requires-Dist: pydantic>=2.9.2
Requires-Dist: requests>=2.32.3
Requires-Dist: restfly>=1.5.0
Requires-Dist: rich>=13.9.3
Requires-Dist: tomlkit>=0.13.2
Requires-Dist: typer>=0.12.5
Provides-Extra: testing
Requires-Dist: pytest-cov>=6.0.0; extra == 'testing'
Requires-Dist: pytest>=8.3.3; extra == 'testing'
Requires-Dist: responses>=0.25.3; extra == 'testing'
Requires-Dist: ruff>=0.7.1; extra == 'testing'
